<?xml version="1.0" encoding="utf-8" ?>
<dwsync>
<file name="banner.gif" server="mhsweb1.com//carter/" local="127572936600000000" remote="129791303400000000" />
<file name="button_album.gif" server="mhsweb1.com//carter/" local="127576215000000000" remote="129791303400000000" />
<file name="button_video.gif" server="mhsweb1.com//carter/" local="127576218000000000" remote="129791303400000000" />
<file name="green_fade.gif" server="mhsweb1.com//carter/" local="127615198800000000" remote="129791303400000000" />
<file name="logo_1stvideo.gif" server="mhsweb1.com//carter/" local="127615405800000000" remote="129791303400000000" />
<file name="logo_bikehike.gif" server="mhsweb1.com//carter/" local="127615200000000000" remote="129791303400000000" />
<file name="logo_newwave.gif" server="mhsweb1.com//carter/" local="127615405800000000" remote="129791303400000000" />
<file name="logo_standard.gif" server="mhsweb1.com//carter/" local="127615405200000000" remote="129791303400000000" />
<file name="nav_contact_off.gif" server="mhsweb1.com//carter/" local="127615203000000000" remote="129791303400000000" />
<file name="nav_contact_on.gif" server="mhsweb1.com//carter/" local="127615204800000000" remote="129791303400000000" />
<file name="nav_donate_off.gif" server="mhsweb1.com//carter/" local="127615203000000000" remote="129791303400000000" />
<file name="nav_donate_on.gif" server="mhsweb1.com//carter/" local="127615204800000000" remote="129791303400000000" />
<file name="nav_home_off.gif" server="mhsweb1.com//carter/" local="127615202400000000" remote="129791303400000000" />
<file name="nav_home_on.gif" server="mhsweb1.com//carter/" local="127615201800000000" remote="129791303400000000" />
<file name="nav_register_off.gif" server="mhsweb1.com//carter/" local="127615202400000000" remote="129791303400000000" />
<file name="nav_register_on.gif" server="mhsweb1.com//carter/" local="127615204200000000" remote="129791303400000000" />
<file name="nav_scrapbook_off.gif" server="mhsweb1.com//carter/" local="127615203000000000" remote="129791303400000000" />
<file name="nav_scrapbook_on.gif" server="mhsweb1.com//carter/" local="127615204800000000" remote="129791303400000000" />
<file name="nav_sponsors_off.gif" server="mhsweb1.com//carter/" local="127615202400000000" remote="129791303400000000" />
<file name="nav_sponsors_on.gif" server="mhsweb1.com//carter/" local="127615204200000000" remote="129791303400000000" />
<file name="image_map.gif" server="mhsweb1.com//carter/" local="127615377000000000" remote="129791303400000000" />
<file name="bike.jpg" server="mhsweb1.com//carter/" local="129717988540000000" remote="129791303400000000" />
<file name="title_animate.gif" server="mhsweb1.com//carter/" local="127576533000000000" remote="129791303400000000" />
<file name="banner_01.gif" server="mhsweb1.com//carter/" local="127576626600000000" remote="129791303400000000" />
<file name="banner_02.gif" server="mhsweb1.com//carter/" local="127576627200000000" remote="129791303400000000" />
<file name="button_funds.gif" server="mhsweb1.com//carter/" local="127576585800000000" remote="129791303400000000" />
<file name="button_resale.gif" server="mhsweb1.com//carter/" local="127576585800000000" remote="129791303400000000" />
<file name="green_fade.gif" server="mhsweb2.com//carter/" local="129949682580000000" remote="129954763200000000" />
<file name="banner.gif" server="mhsweb2.com//carter/" local="129949682620000000" remote="129954763200000000" />
<file name="nav_home_on.gif" server="mhsweb2.com//carter/" local="129949682540000000" remote="129954763200000000" />
<file name="nav_register_off.gif" server="mhsweb2.com//carter/" local="129949682540000000" remote="129954763200000000" />
<file name="nav_sponsors_off.gif" server="mhsweb2.com//carter/" local="129949682500000000" remote="129954763200000000" />
<file name="nav_donate_off.gif" server="mhsweb2.com//carter/" local="129949682560000000" remote="129954763200000000" />
<file name="nav_scrapbook_off.gif" server="mhsweb2.com//carter/" local="129949682520000000" remote="129954763200000000" />
<file name="nav_contact_off.gif" server="mhsweb2.com//carter/" local="129949682560000000" remote="129954763200000000" />
<file name="logo_bikehike.gif" server="mhsweb2.com//carter/" local="129949682580000000" remote="129954763200000000" />
<file name="image_map.gif" server="mhsweb2.com//carter/" local="129949682580000000" remote="129954763200000000" />
</dwsync>